{
  "id": "forest",
  "name": "Forest",
  "description": "Dense woodland. Ancient trees, ruins, and fairy circles.",
  "type": "single",
  "zoneStyle": "Forest",
  "bounds": {
    "minX": -400,
    "maxX": 400,
    "minZ": -400,
    "maxZ": 400
  },
  "spawn": {
    "x": 0,
    "y": 1,
    "z": -13
  },
  "terrain": {
    "profile": "hills"
  },
  "theme": {
    "colors": {
      "ground": "#8F9779",
      "soil": "#8F9779",
      "sand": "#8F9779",
      "rock": "#708090",
      "accent": "#6B8E23"
    }
  },
  "structures": [
    {
      "type": "village",
      "position": {
        "x": 0,
        "z": 0
      },
      "rotation": 0,
      "scale": 1
    },
    {
      "type": "house",
      "position": {
        "x": 31,
        "z": -17
      },
      "rotation": 1.82212373908208,
      "scale": 0.9939903718419373
    },
    {
      "type": "tavern",
      "position": {
        "x": -13,
        "z": -33
      },
      "rotation": 3.078760800517997,
      "scale": 1.0645159554667771
    },
    {
      "type": "shop",
      "position": {
        "x": -16,
        "z": 28
      },
      "rotation": 1.0053096491487339,
      "scale": 0.9214853447861969
    },
    {
      "type": "temple",
      "position": {
        "x": 16,
        "z": 28
      },
      "rotation": 3.7699111843077517,
      "scale": 0.9836332810111343
    },
    {
      "type": "house",
      "position": {
        "x": -34,
        "z": 3
      },
      "rotation": 4.71238898038469,
      "scale": 1.083464036602527
    },
    {
      "type": "house",
      "position": {
        "x": 31,
        "z": 8
      },
      "rotation": 5.215043804959056,
      "scale": 1.001626415271312
    },
    {
      "type": "village_fence",
      "position": {
        "x": 50,
        "z": 0
      },
      "rotation": 1.5707963267948966,
      "scale": 1
    },
    {
      "type": "village_fence",
      "position": {
        "x": 49,
        "z": 9
      },
      "rotation": 1.7453292519943295,
      "scale": 1
    },
    {
      "type": "village_fence",
      "position": {
        "x": 47,
        "z": 17
      },
      "rotation": 1.9198621771937625,
      "scale": 1
    },
    {
      "type": "village_fence",
      "position": {
        "x": 43,
        "z": 25
      },
      "rotation": 2.0943951023931953,
      "scale": 1
    },
    {
      "type": "village_fence",
      "position": {
        "x": 38,
        "z": 32
      },
      "rotation": 2.2689280275926285,
      "scale": 1
    },
    {
      "type": "village_fence",
      "position": {
        "x": 32,
        "z": 38
      },
      "rotation": 2.443460952792061,
      "scale": 1
    },
    {
      "type": "village_fence",
      "position": {
        "x": 25,
        "z": 43
      },
      "rotation": 2.617993877991494,
      "scale": 1
    },
    {
      "type": "village_fence",
      "position": {
        "x": 17,
        "z": 47
      },
      "rotation": 2.792526803190927,
      "scale": 1
    },
    {
      "type": "village_fence",
      "position": {
        "x": 9,
        "z": 49
      },
      "rotation": 2.9670597283903604,
      "scale": 1
    },
    {
      "type": "village_fence",
      "position": {
        "x": 0,
        "z": 50
      },
      "rotation": 3.141592653589793,
      "scale": 1
    },
    {
      "type": "village_fence",
      "position": {
        "x": -9,
        "z": 49
      },
      "rotation": 3.316125578789226,
      "scale": 1
    },
    {
      "type": "village_fence",
      "position": {
        "x": -17,
        "z": 47
      },
      "rotation": 3.490658503988659,
      "scale": 1
    },
    {
      "type": "village_fence",
      "position": {
        "x": -25,
        "z": 43
      },
      "rotation": 3.665191429188092,
      "scale": 1
    },
    {
      "type": "village_fence",
      "position": {
        "x": -32,
        "z": 38
      },
      "rotation": 3.839724354387525,
      "scale": 1
    },
    {
      "type": "village_fence",
      "position": {
        "x": -38,
        "z": 32
      },
      "rotation": 4.014257279586958,
      "scale": 1
    },
    {
      "type": "village_fence",
      "position": {
        "x": -43,
        "z": 25
      },
      "rotation": 4.188790204786391,
      "scale": 1
    },
    {
      "type": "village_fence",
      "position": {
        "x": -47,
        "z": 17
      },
      "rotation": 4.363323129985824,
      "scale": 1
    },
    {
      "type": "village_fence",
      "position": {
        "x": -49,
        "z": 9
      },
      "rotation": 4.537856055185257,
      "scale": 1
    },
    {
      "type": "village_fence",
      "position": {
        "x": -50,
        "z": 0
      },
      "rotation": 4.71238898038469,
      "scale": 1
    },
    {
      "type": "village_fence",
      "position": {
        "x": -49,
        "z": -9
      },
      "rotation": 4.886921905584122,
      "scale": 1
    },
    {
      "type": "village_fence",
      "position": {
        "x": -47,
        "z": -17
      },
      "rotation": 5.061454830783555,
      "scale": 1
    },
    {
      "type": "village_fence",
      "position": {
        "x": -43,
        "z": -25
      },
      "rotation": 5.235987755982989,
      "scale": 1
    },
    {
      "type": "village_fence",
      "position": {
        "x": -38,
        "z": -32
      },
      "rotation": 5.410520681182422,
      "scale": 1
    },
    {
      "type": "village_fence",
      "position": {
        "x": -32,
        "z": -38
      },
      "rotation": 5.585053606381854,
      "scale": 1
    },
    {
      "type": "village_fence",
      "position": {
        "x": -25,
        "z": -43
      },
      "rotation": 5.759586531581287,
      "scale": 1
    },
    {
      "type": "village_fence",
      "position": {
        "x": -17,
        "z": -47
      },
      "rotation": 5.93411945678072,
      "scale": 1
    },
    {
      "type": "village_gate",
      "position": {
        "x": 0,
        "z": -50
      },
      "rotation": 0,
      "scale": 1
    },
    {
      "type": "cave",
      "position": {
        "x": -278,
        "z": -207
      },
      "rotation": 2.4504422698000385,
      "scale": 0.930838305130601
    },
    {
      "type": "cave",
      "position": {
        "x": -4,
        "z": -202
      },
      "rotation": 5.717698629533424,
      "scale": 0.9631914917379618
    },
    {
      "type": "cave",
      "position": {
        "x": 99,
        "z": -290
      },
      "rotation": 0.4398229715025711,
      "scale": 0.9879046026617289
    },
    {
      "type": "cave",
      "position": {
        "x": 206,
        "z": -275
      },
      "rotation": 4.084070449666731,
      "scale": 1.039254981651902
    },
    {
      "type": "cave",
      "position": {
        "x": -190,
        "z": -40
      },
      "rotation": 2.3876104167282426,
      "scale": 1.0577699724584817
    },
    {
      "type": "cave",
      "position": {
        "x": -73,
        "z": -58
      },
      "rotation": 6.094689747964199,
      "scale": 1.0902269188314677
    },
    {
      "type": "cave",
      "position": {
        "x": 37,
        "z": -32
      },
      "rotation": 0.7539822368615503,
      "scale": 1.0896531645208598
    },
    {
      "type": "cave",
      "position": {
        "x": 295,
        "z": -84
      },
      "rotation": 2.8902652413026098,
      "scale": 0.9153260532766581
    },
    {
      "type": "cave",
      "position": {
        "x": -337,
        "z": 95
      },
      "rotation": 3.8327430373795477,
      "scale": 0.9327729288488626
    },
    {
      "type": "cave",
      "position": {
        "x": -16,
        "z": 52
      },
      "rotation": 1.0053096491487339,
      "scale": 1.0137711349874734
    }
  ],
  "environment": [
    {
      "type": "small_mushroom",
      "position": {
        "x": 92,
        "z": -273
      },
      "scale": 1.2662547593005002
    },
    {
      "type": "small_plant",
      "position": {
        "x": -260,
        "z": 74
      },
      "scale": 1.2658031647093595
    },
    {
      "type": "bush",
      "position": {
        "x": 221,
        "z": 328
      },
      "scale": 1.2574311141856014
    },
    {
      "type": "rare_plant",
      "position": {
        "x": -172,
        "z": -302
      },
      "scale": 1.1234384124167263
    },
    {
      "type": "small_plant",
      "position": {
        "x": -126,
        "z": 223
      },
      "scale": 0.853937364090234
    },
    {
      "type": "forest_debris",
      "position": {
        "x": 12,
        "z": -70
      },
      "scale": 0.8468527738936245
    },
    {
      "type": "forest_shrine",
      "position": {
        "x": 36,
        "z": -323
      },
      "scale": 1.0079219465143978
    },
    {
      "type": "tree",
      "position": {
        "x": 240,
        "z": -90
      },
      "scale": 1.050694686640054
    },
    {
      "type": "bush",
      "position": {
        "x": 339,
        "z": 305
      },
      "scale": 0.7965332989580929
    },
    {
      "type": "magical_flower",
      "position": {
        "x": -170,
        "z": 128
      },
      "scale": 1.0746125881560147
    },
    {
      "type": "bush",
      "position": {
        "x": -211,
        "z": 33
      },
      "scale": 1.0219198589213192
    },
    {
      "type": "ancient_tree",
      "position": {
        "x": 352,
        "z": 264
      },
      "scale": 0.7832549159415065
    },
    {
      "type": "treehouse",
      "position": {
        "x": 357,
        "z": 295
      },
      "scale": 1.2112300639040767
    },
    {
      "type": "tree",
      "position": {
        "x": -137,
        "z": -91
      },
      "scale": 1.1662701074965298
    },
    {
      "type": "tree",
      "position": {
        "x": -211,
        "z": 277
      },
      "scale": 0.8166123514063656
    },
    {
      "type": "glowing_flowers",
      "position": {
        "x": 113,
        "z": 2
      },
      "scale": 0.7383066003210842
    },
    {
      "type": "tree_cluster",
      "position": {
        "x": 237,
        "z": -206
      },
      "scale": 1.0152151589281857
    },
    {
      "type": "tree_cluster",
      "position": {
        "x": 61,
        "z": -46
      },
      "scale": 0.9390128319151699
    },
    {
      "type": "berry_bush",
      "position": {
        "x": 346,
        "z": 10
      },
      "scale": 1.1091869239695369
    },
    {
      "type": "magical_flower",
      "position": {
        "x": 194,
        "z": -196
      },
      "scale": 0.7330372397787869
    },
    {
      "type": "stone_circle",
      "position": {
        "x": 288,
        "z": -158
      },
      "scale": 0.9256760840304196
    },
    {
      "type": "tree",
      "position": {
        "x": -348,
        "z": 222
      },
      "scale": 0.8100282614119351
    },
    {
      "type": "ancient_tree",
      "position": {
        "x": 329,
        "z": 273
      },
      "scale": 0.8168310766108333
    },
    {
      "type": "tree_cluster",
      "position": {
        "x": -177,
        "z": 349
      },
      "scale": 1.1846343343146144
    },
    {
      "type": "overgrown_ruin",
      "position": {
        "x": 100,
        "z": 39
      },
      "scale": 1.0598003392107784
    },
    {
      "type": "tall_grass",
      "position": {
        "x": 26,
        "z": -45
      },
      "scale": 1.196503895986825
    },
    {
      "type": "stone_circle",
      "position": {
        "x": 47,
        "z": -55
      },
      "scale": 1.2567323093302547
    },
    {
      "type": "glowing_flowers",
      "position": {
        "x": -330,
        "z": 160
      },
      "scale": 0.7102853839285671
    },
    {
      "type": "fern",
      "position": {
        "x": -18,
        "z": -14
      },
      "scale": 0.9347754244692623
    },
    {
      "type": "stone_circle",
      "position": {
        "x": -307,
        "z": -166
      },
      "scale": 0.7156272356398403
    },
    {
      "type": "rare_plant",
      "position": {
        "x": -190,
        "z": 67
      },
      "scale": 0.7460781221278011
    },
    {
      "type": "berry_bush",
      "position": {
        "x": -316,
        "z": -83
      },
      "scale": 0.9271778886206448
    },
    {
      "type": "berry_bush",
      "position": {
        "x": 244,
        "z": 4
      },
      "scale": 1.2677888398058712
    },
    {
      "type": "small_mushroom",
      "position": {
        "x": 42,
        "z": -181
      },
      "scale": 0.9845857803709804
    },
    {
      "type": "treehouse",
      "position": {
        "x": -72,
        "z": 241
      },
      "scale": 1.2020560150034725
    },
    {
      "type": "glowing_flowers",
      "position": {
        "x": -185,
        "z": 300
      },
      "scale": 1.0524993483908474
    },
    {
      "type": "glowing_flowers",
      "position": {
        "x": -245,
        "z": -307
      },
      "scale": 0.9760280852206051
    },
    {
      "type": "tall_grass",
      "position": {
        "x": 302,
        "z": -130
      },
      "scale": 1.2205670301802456
    },
    {
      "type": "tall_grass",
      "position": {
        "x": -11,
        "z": 66
      },
      "scale": 0.9418534879572689
    },
    {
      "type": "fairy_circle",
      "position": {
        "x": 11,
        "z": -171
      },
      "scale": 0.9034372632391751
    },
    {
      "type": "mushroom_cluster",
      "position": {
        "x": 264,
        "z": 95
      },
      "scale": 0.776680660713464
    },
    {
      "type": "stone_circle",
      "position": {
        "x": -298,
        "z": -52
      },
      "scale": 1.2407584850676359
    },
    {
      "type": "stone_circle",
      "position": {
        "x": 303,
        "z": -136
      },
      "scale": 1.2826580409891903
    },
    {
      "type": "fern",
      "position": {
        "x": 223,
        "z": -93
      },
      "scale": 0.8971791331656277
    },
    {
      "type": "berry_bush",
      "position": {
        "x": -80,
        "z": 89
      },
      "scale": 0.7869340662844478
    },
    {
      "type": "bush",
      "position": {
        "x": 353,
        "z": 15
      },
      "scale": 0.8623476450331509
    },
    {
      "type": "forest_shrine",
      "position": {
        "x": -261,
        "z": -45
      },
      "scale": 1.1416571740992367
    },
    {
      "type": "fallen_log",
      "position": {
        "x": -320,
        "z": -228
      },
      "scale": 0.8509124581702053
    },
    {
      "type": "forest_flower",
      "position": {
        "x": -246,
        "z": -3
      },
      "scale": 1.1239758019335566
    },
    {
      "type": "magical_flower",
      "position": {
        "x": 43,
        "z": 29
      },
      "scale": 1.102522010076791
    },
    {
      "type": "bush",
      "position": {
        "x": 47,
        "z": -60
      },
      "scale": 1.2360383872874081
    },
    {
      "type": "tree_cluster",
      "position": {
        "x": -230,
        "z": 106
      },
      "scale": 1.181824738252908
    },
    {
      "type": "stone_circle",
      "position": {
        "x": 74,
        "z": 138
      },
      "scale": 0.7049933676607907
    },
    {
      "type": "berry_bush",
      "position": {
        "x": 161,
        "z": -47
      },
      "scale": 1.178469080198556
    },
    {
      "type": "magical_flower",
      "position": {
        "x": 97,
        "z": 138
      },
      "scale": 1.0829891805537044
    },
    {
      "type": "small_mushroom",
      "position": {
        "x": -276,
        "z": 150
      },
      "scale": 1.1071034734137355
    },
    {
      "type": "mushroom",
      "position": {
        "x": -250,
        "z": 114
      },
      "scale": 0.8471742634661495
    },
    {
      "type": "mushroom_cluster",
      "position": {
        "x": -62,
        "z": -253
      },
      "scale": 0.9073763553984463
    },
    {
      "type": "small_mushroom",
      "position": {
        "x": 196,
        "z": 152
      },
      "scale": 0.7996970538981258
    },
    {
      "type": "rare_plant",
      "position": {
        "x": 211,
        "z": -136
      },
      "scale": 1.0439361636526883
    },
    {
      "type": "mushroom",
      "position": {
        "x": -189,
        "z": 246
      },
      "scale": 1.0677059893496335
    },
    {
      "type": "overgrown_ruin",
      "position": {
        "x": 42,
        "z": 91
      },
      "scale": 0.7064313356764614
    },
    {
      "type": "stone_circle",
      "position": {
        "x": -64,
        "z": 301
      },
      "scale": 1.1033495073206723
    },
    {
      "type": "forest_shrine",
      "position": {
        "x": -260,
        "z": -72
      },
      "scale": 0.8095103089697658
    },
    {
      "type": "giant_mushroom",
      "position": {
        "x": -154,
        "z": 133
      },
      "scale": 0.8837760453112423
    },
    {
      "type": "treehouse",
      "position": {
        "x": -296,
        "z": 226
      },
      "scale": 0.9928215210326015
    },
    {
      "type": "fairy_circle",
      "position": {
        "x": 345,
        "z": 186
      },
      "scale": 0.9111340408213436
    },
    {
      "type": "bush",
      "position": {
        "x": -299,
        "z": 304
      },
      "scale": 0.8210134093649685
    },
    {
      "type": "rare_plant",
      "position": {
        "x": 165,
        "z": 96
      },
      "scale": 1.0125719313509762
    },
    {
      "type": "glowing_flowers",
      "position": {
        "x": 311,
        "z": 112
      },
      "scale": 0.9837344114668667
    },
    {
      "type": "giant_mushroom",
      "position": {
        "x": 292,
        "z": 128
      },
      "scale": 0.94023815440014
    },
    {
      "type": "berry_bush",
      "position": {
        "x": 43,
        "z": 231
      },
      "scale": 0.8956329648382961
    },
    {
      "type": "fairy_circle",
      "position": {
        "x": 358,
        "z": -263
      },
      "scale": 0.971281147468835
    },
    {
      "type": "giant_mushroom",
      "position": {
        "x": -346,
        "z": -289
      },
      "scale": 1.0963575069792568
    },
    {
      "type": "fern",
      "position": {
        "x": 87,
        "z": -272
      },
      "scale": 0.7078493480570613
    },
    {
      "type": "tree_cluster",
      "position": {
        "x": -5,
        "z": -329
      },
      "scale": 0.8505564753897488
    },
    {
      "type": "overgrown_ruin",
      "position": {
        "x": 13,
        "z": 95
      },
      "scale": 0.8770911936648189
    },
    {
      "type": "fern",
      "position": {
        "x": -158,
        "z": -298
      },
      "scale": 1.1478783075697718
    },
    {
      "type": "fern",
      "position": {
        "x": 40,
        "z": 25
      },
      "scale": 0.9311551217921078
    },
    {
      "type": "treehouse",
      "position": {
        "x": 226,
        "z": 25
      },
      "scale": 1.1029714410193263
    },
    {
      "type": "fern",
      "position": {
        "x": 161,
        "z": 52
      },
      "scale": 0.8471895699389278
    },
    {
      "type": "fairy_circle",
      "position": {
        "x": 105,
        "z": 48
      },
      "scale": 0.9554843132384121
    },
    {
      "type": "mushroom",
      "position": {
        "x": -261,
        "z": -99
      },
      "scale": 1.127342975605279
    },
    {
      "type": "mushroom",
      "position": {
        "x": -33,
        "z": -188
      },
      "scale": 0.8700653617270291
    },
    {
      "type": "bush",
      "position": {
        "x": -330,
        "z": -73
      },
      "scale": 0.9987637762911616
    },
    {
      "type": "forest_flower",
      "position": {
        "x": -329,
        "z": -13
      },
      "scale": 0.9363630239851772
    },
    {
      "type": "fern",
      "position": {
        "x": 215,
        "z": -324
      },
      "scale": 0.8136004094965755
    },
    {
      "type": "tree_cluster",
      "position": {
        "x": -114,
        "z": -287
      },
      "scale": 1.1690257375128565
    },
    {
      "type": "fallen_log",
      "position": {
        "x": 289,
        "z": 43
      },
      "scale": 0.8490013127215206
    },
    {
      "type": "small_mushroom",
      "position": {
        "x": -70,
        "z": 201
      },
      "scale": 0.9077019398100674
    },
    {
      "type": "forest_debris",
      "position": {
        "x": 336,
        "z": -329
      },
      "scale": 0.7071149234659969
    },
    {
      "type": "berry_bush",
      "position": {
        "x": -67,
        "z": -311
      },
      "scale": 1.2170400683768094
    },
    {
      "type": "forest_shrine",
      "position": {
        "x": 169,
        "z": -2
      },
      "scale": 1.1150896792300045
    },
    {
      "type": "flower",
      "position": {
        "x": 112,
        "z": -70
      },
      "scale": 1.2866885607130825
    },
    {
      "type": "stone_circle",
      "position": {
        "x": -308,
        "z": 207
      },
      "scale": 0.9250740175135433
    },
    {
      "type": "small_plant",
      "position": {
        "x": 57,
        "z": -298
      },
      "scale": 0.831295854318887
    },
    {
      "type": "treehouse",
      "position": {
        "x": 338,
        "z": 114
      },
      "scale": 0.7142163758166133
    },
    {
      "type": "tree_cluster",
      "position": {
        "x": 166,
        "z": -145
      },
      "scale": 1.2905103866942227
    },
    {
      "type": "berry_bush",
      "position": {
        "x": 32,
        "z": 164
      },
      "scale": 0.9846651916392146
    },
    {
      "type": "giant_mushroom",
      "position": {
        "x": 208,
        "z": -290
      },
      "scale": 1.0289805953390896
    },
    {
      "type": "flower",
      "position": {
        "x": -334,
        "z": -8
      },
      "scale": 0.9635689024813472
    },
    {
      "type": "giant_mushroom",
      "position": {
        "x": 41,
        "z": -63
      },
      "scale": 0.7363549177534878
    },
    {
      "type": "overgrown_ruin",
      "position": {
        "x": 225,
        "z": -138
      },
      "scale": 1.003075945843011
    },
    {
      "type": "mushroom_cluster",
      "position": {
        "x": 334,
        "z": -325
      },
      "scale": 1.0272817914374173
    },
    {
      "type": "giant_mushroom",
      "position": {
        "x": -97,
        "z": -49
      },
      "scale": 0.7803347592242061
    },
    {
      "type": "glowing_flowers",
      "position": {
        "x": -314,
        "z": 136
      },
      "scale": 1.2414096538908779
    },
    {
      "type": "small_plant",
      "position": {
        "x": -138,
        "z": 343
      },
      "scale": 1.0974937801249325
    },
    {
      "type": "small_plant",
      "position": {
        "x": -334,
        "z": 278
      },
      "scale": 1.2433869426138697
    },
    {
      "type": "rare_plant",
      "position": {
        "x": -83,
        "z": 314
      },
      "scale": 0.8817014460451901
    },
    {
      "type": "mushroom",
      "position": {
        "x": -228,
        "z": -307
      },
      "scale": 0.8228620951063931
    },
    {
      "type": "treehouse",
      "position": {
        "x": -29,
        "z": -233
      },
      "scale": 0.7851061944849789
    },
    {
      "type": "glowing_flowers",
      "position": {
        "x": 313,
        "z": 39
      },
      "scale": 0.8944835488684475
    },
    {
      "type": "mushroom_cluster",
      "position": {
        "x": 18,
        "z": -41
      },
      "scale": 0.7848564629442989
    },
    {
      "type": "berry_bush",
      "position": {
        "x": 247,
        "z": 8
      },
      "scale": 1.097899741400033
    },
    {
      "type": "overgrown_ruin",
      "position": {
        "x": 142,
        "z": -105
      },
      "scale": 0.7831006889231502
    },
    {
      "type": "forest_debris",
      "position": {
        "x": 64,
        "z": 359
      },
      "scale": 0.99775911020115
    },
    {
      "type": "tree_cluster",
      "position": {
        "x": -204,
        "z": -71
      },
      "scale": 1.2069873099215327
    },
    {
      "type": "fairy_circle",
      "position": {
        "x": 341,
        "z": 322
      },
      "scale": 1.2837100927717984
    },
    {
      "type": "forest_debris",
      "position": {
        "x": -37,
        "z": 327
      },
      "scale": 1.2086647634394465
    },
    {
      "type": "tall_grass",
      "position": {
        "x": 308,
        "z": -242
      },
      "scale": 0.7704011266119778
    },
    {
      "type": "tree",
      "position": {
        "x": 279,
        "z": -177
      },
      "scale": 1.0652814869768916
    },
    {
      "type": "tree",
      "position": {
        "x": 3,
        "z": -123
      },
      "scale": 1.1974806492216885
    },
    {
      "type": "small_plant",
      "position": {
        "x": -254,
        "z": -57
      },
      "scale": 0.978985918033868
    },
    {
      "type": "small_plant",
      "position": {
        "x": 275,
        "z": 358
      },
      "scale": 1.2295970981009305
    },
    {
      "type": "tall_grass",
      "position": {
        "x": 337,
        "z": -37
      },
      "scale": 1.0769264941103756
    },
    {
      "type": "ancient_tree",
      "position": {
        "x": -98,
        "z": 71
      },
      "scale": 1.2563989107497036
    },
    {
      "type": "small_plant",
      "position": {
        "x": -202,
        "z": -214
      },
      "scale": 0.8112516527064144
    },
    {
      "type": "stone_circle",
      "position": {
        "x": -86,
        "z": -42
      },
      "scale": 0.992534524668008
    },
    {
      "type": "tree_cluster",
      "position": {
        "x": 280,
        "z": -52
      },
      "scale": 0.7591098313219845
    },
    {
      "type": "treehouse",
      "position": {
        "x": -12,
        "z": 147
      },
      "scale": 1.2776523773558437
    },
    {
      "type": "flower",
      "position": {
        "x": -291,
        "z": 174
      },
      "scale": 0.8226494674570858
    },
    {
      "type": "forest_debris",
      "position": {
        "x": -106,
        "z": -41
      },
      "scale": 1.0764009063132107
    },
    {
      "type": "small_mushroom",
      "position": {
        "x": -303,
        "z": 99
      },
      "scale": 0.8290189986117183
    },
    {
      "type": "tree_cluster",
      "position": {
        "x": 211,
        "z": 64
      },
      "scale": 1.0784285490401089
    },
    {
      "type": "ancient_tree",
      "position": {
        "x": -211,
        "z": -11
      },
      "scale": 1.1303668622858822
    },
    {
      "type": "forest_shrine",
      "position": {
        "x": 166,
        "z": 322
      },
      "scale": 1.2983837430365384
    },
    {
      "type": "flower",
      "position": {
        "x": 337,
        "z": 18
      },
      "scale": 0.8038414959795772
    },
    {
      "type": "giant_mushroom",
      "position": {
        "x": -201,
        "z": -217
      },
      "scale": 1.075914925802499
    },
    {
      "type": "tree",
      "position": {
        "x": 347,
        "z": 272
      },
      "scale": 1.2515913371928036
    },
    {
      "type": "treehouse",
      "position": {
        "x": -42,
        "z": 288
      },
      "scale": 0.875670534837991
    },
    {
      "type": "stone_circle",
      "position": {
        "x": 350,
        "z": 24
      },
      "scale": 0.8007648234255611
    },
    {
      "type": "small_mushroom",
      "position": {
        "x": 142,
        "z": -15
      },
      "scale": 1.087299007643014
    },
    {
      "type": "bush",
      "position": {
        "x": 252,
        "z": -98
      },
      "scale": 0.7035103921778499
    },
    {
      "type": "fairy_circle",
      "position": {
        "x": -60,
        "z": -184
      },
      "scale": 0.8254487817175686
    },
    {
      "type": "forest_shrine",
      "position": {
        "x": 45,
        "z": -281
      },
      "scale": 0.93697648094967
    }
  ],
  "paths": [
    {
      "id": "cave_0",
      "points": [
        {
          "x": -278.2,
          "y": -1.2,
          "z": -206.9
        },
        {
          "x": -272.9,
          "y": -1.1,
          "z": -199.4
        },
        {
          "x": -268.9,
          "y": -0.7,
          "z": -191.6
        },
        {
          "x": -266.4,
          "y": -0.1,
          "z": -184.1
        },
        {
          "x": -262.1,
          "y": -0.1,
          "z": -175.5
        },
        {
          "x": -257.1,
          "y": -0.6,
          "z": -167.8
        },
        {
          "x": -252.6,
          "y": -1.3,
          "z": -158.4
        },
        {
          "x": -249.2,
          "y": -1.7,
          "z": -151.6
        },
        {
          "x": -244.8,
          "y": -2.5,
          "z": -143.2
        },
        {
          "x": -240.4,
          "y": -3.1,
          "z": -135.4
        },
        {
          "x": -235.4,
          "y": -3,
          "z": -127.4
        },
        {
          "x": -231.5,
          "y": -3,
          "z": -118.8
        },
        {
          "x": -228.5,
          "y": -3,
          "z": -111.7
        },
        {
          "x": -223.4,
          "y": -2.5,
          "z": -104.4
        },
        {
          "x": -218.8,
          "y": -1.6,
          "z": -95.2
        },
        {
          "x": -215.7,
          "y": -1.2,
          "z": -88.3
        },
        {
          "x": -210.1,
          "y": -0.6,
          "z": -80.1
        },
        {
          "x": -205.9,
          "y": -0.1,
          "z": -71.9
        },
        {
          "x": -203,
          "y": -0.3,
          "z": -63.1
        },
        {
          "x": -198.6,
          "y": -0.8,
          "z": -56
        },
        {
          "x": -193.3,
          "y": -1.5,
          "z": -48.4
        },
        {
          "x": -190.2,
          "y": -2,
          "z": -40.6
        }
      ]
    },
    {
      "id": "cave_1",
      "points": [
        {
          "x": -190.2,
          "y": -2,
          "z": -40.4
        },
        {
          "x": -180.3,
          "y": -2.8,
          "z": -40.9
        },
        {
          "x": -171.2,
          "y": -3,
          "z": -41.9
        },
        {
          "x": -162.1,
          "y": -3.2,
          "z": -43.2
        },
        {
          "x": -153.2,
          "y": -3.3,
          "z": -46.2
        },
        {
          "x": -145.6,
          "y": -3.6,
          "z": -46.3
        },
        {
          "x": -136.2,
          "y": -3.9,
          "z": -47.5
        },
        {
          "x": -127.9,
          "y": -3.9,
          "z": -48.7
        },
        {
          "x": -117,
          "y": -4.2,
          "z": -52
        },
        {
          "x": -109.1,
          "y": -4.3,
          "z": -52.9
        },
        {
          "x": -100,
          "y": -4.1,
          "z": -53.4
        },
        {
          "x": -90.4,
          "y": -3.7,
          "z": -55.3
        },
        {
          "x": -82.6,
          "y": -3.3,
          "z": -57.4
        },
        {
          "x": -72.5,
          "y": -2.6,
          "z": -57.7
        }
      ]
    },
    {
      "id": "cave_2",
      "points": [
        {
          "x": -73.1,
          "y": -2.7,
          "z": -57
        },
        {
          "x": -64.1,
          "y": -2.4,
          "z": -56.6
        },
        {
          "x": -55.1,
          "y": -2,
          "z": -53.8
        },
        {
          "x": -46.8,
          "y": -1.5,
          "z": -51.2
        },
        {
          "x": -38.7,
          "y": -0.9,
          "z": -51
        },
        {
          "x": -29.8,
          "y": -0.2,
          "z": -48.2
        },
        {
          "x": -22.8,
          "y": 0,
          "z": -45.3
        },
        {
          "x": -13,
          "y": 0.1,
          "z": -43.7
        },
        {
          "x": -5,
          "y": -0.1,
          "z": -41.9
        },
        {
          "x": 3.1,
          "y": -0.2,
          "z": -41
        },
        {
          "x": 10.8,
          "y": -1.3,
          "z": -37.1
        },
        {
          "x": 20.8,
          "y": -1.5,
          "z": -36.7
        },
        {
          "x": 28.1,
          "y": -1.6,
          "z": -33.4
        },
        {
          "x": 37.9,
          "y": -1.5,
          "z": -32.7
        }
      ]
    },
    {
      "id": "cave_3",
      "points": [
        {
          "x": 36.9,
          "y": -1.6,
          "z": -31.6
        },
        {
          "x": 32.3,
          "y": -2.4,
          "z": -24
        },
        {
          "x": 26.5,
          "y": -3,
          "z": -17.2
        },
        {
          "x": 23.3,
          "y": -4,
          "z": -8.4
        },
        {
          "x": 17.8,
          "y": -4.9,
          "z": -0.8
        },
        {
          "x": 13.4,
          "y": -5.8,
          "z": 5.2
        },
        {
          "x": 7.2,
          "y": -7.5,
          "z": 14.4
        },
        {
          "x": 3.7,
          "y": -8.4,
          "z": 21
        },
        {
          "x": -2,
          "y": -8.8,
          "z": 28.1
        },
        {
          "x": -6.4,
          "y": -9,
          "z": 37.3
        },
        {
          "x": -10.7,
          "y": -8.9,
          "z": 43.8
        },
        {
          "x": -15,
          "y": -8.9,
          "z": 52.6
        }
      ]
    },
    {
      "id": "cave_4",
      "points": [
        {
          "x": -73.1,
          "y": -2.6,
          "z": -58.1
        },
        {
          "x": -69.3,
          "y": -1.7,
          "z": -66.7
        },
        {
          "x": -66.1,
          "y": -0.9,
          "z": -73.1
        },
        {
          "x": -60.8,
          "y": 0.7,
          "z": -81.5
        },
        {
          "x": -57.9,
          "y": 2,
          "z": -89.6
        },
        {
          "x": -53.9,
          "y": 3.3,
          "z": -97.8
        },
        {
          "x": -49.3,
          "y": 4.9,
          "z": -105.6
        },
        {
          "x": -46.2,
          "y": 6.1,
          "z": -113.2
        },
        {
          "x": -41.4,
          "y": 7.1,
          "z": -122
        },
        {
          "x": -38.5,
          "y": 7.5,
          "z": -130
        },
        {
          "x": -34.9,
          "y": 7.6,
          "z": -138.1
        },
        {
          "x": -31.7,
          "y": 7.2,
          "z": -146.2
        },
        {
          "x": -27,
          "y": 7,
          "z": -154.6
        },
        {
          "x": -23.5,
          "y": 6.9,
          "z": -162.6
        },
        {
          "x": -20.2,
          "y": 6.6,
          "z": -170.3
        },
        {
          "x": -15.6,
          "y": 6.4,
          "z": -178
        },
        {
          "x": -11.7,
          "y": 6,
          "z": -185.2
        },
        {
          "x": -6.9,
          "y": 5,
          "z": -193.5
        },
        {
          "x": -4.1,
          "y": 4.7,
          "z": -201.7
        }
      ]
    },
    {
      "id": "cave_5",
      "points": [
        {
          "x": -4,
          "y": 4.7,
          "z": -202.7
        },
        {
          "x": 3,
          "y": 4.9,
          "z": -208.1
        },
        {
          "x": 10.1,
          "y": 5.4,
          "z": -214.3
        },
        {
          "x": 18.6,
          "y": 5.8,
          "z": -220.5
        },
        {
          "x": 24.8,
          "y": 6.3,
          "z": -227.1
        },
        {
          "x": 32.3,
          "y": 7.2,
          "z": -234
        },
        {
          "x": 40.4,
          "y": 7.6,
          "z": -239.4
        },
        {
          "x": 47.1,
          "y": 7.9,
          "z": -245.9
        },
        {
          "x": 55.1,
          "y": 7.6,
          "z": -251.3
        },
        {
          "x": 62.2,
          "y": 8,
          "z": -259
        },
        {
          "x": 70.6,
          "y": 8.2,
          "z": -264.5
        },
        {
          "x": 76.3,
          "y": 8.2,
          "z": -272
        },
        {
          "x": 84.5,
          "y": 7.9,
          "z": -276.7
        },
        {
          "x": 91.7,
          "y": 8,
          "z": -283.3
        },
        {
          "x": 98.3,
          "y": 7.1,
          "z": -291
        }
      ]
    },
    {
      "id": "cave_6",
      "points": [
        {
          "x": 99,
          "y": 7,
          "z": -289.3
        },
        {
          "x": 107.3,
          "y": 5.8,
          "z": -289.7
        },
        {
          "x": 116.4,
          "y": 5.1,
          "z": -287.8
        },
        {
          "x": 126.2,
          "y": 4.2,
          "z": -286
        },
        {
          "x": 133.7,
          "y": 3.8,
          "z": -285.3
        },
        {
          "x": 142.6,
          "y": 3.9,
          "z": -283.2
        },
        {
          "x": 152.4,
          "y": 4.1,
          "z": -282.3
        },
        {
          "x": 160.7,
          "y": 4.2,
          "z": -281.9
        },
        {
          "x": 169.9,
          "y": 4.8,
          "z": -280.1
        },
        {
          "x": 179.3,
          "y": 5.1,
          "z": -279.7
        },
        {
          "x": 188.4,
          "y": 4.9,
          "z": -276.7
        },
        {
          "x": 196.6,
          "y": 4.5,
          "z": -275.8
        },
        {
          "x": 206.4,
          "y": 4.1,
          "z": -274.9
        }
      ]
    },
    {
      "id": "cave_7",
      "points": [
        {
          "x": -189.9,
          "y": -2,
          "z": -39.8
        },
        {
          "x": -197.8,
          "y": -1.6,
          "z": -33.6
        },
        {
          "x": -204.3,
          "y": -1.5,
          "z": -28.1
        },
        {
          "x": -210.6,
          "y": -1.3,
          "z": -20.6
        },
        {
          "x": -217.3,
          "y": -1.3,
          "z": -14.9
        },
        {
          "x": -224.5,
          "y": -1.6,
          "z": -8.1
        },
        {
          "x": -232.5,
          "y": -1.5,
          "z": -1.4
        },
        {
          "x": -238.1,
          "y": -1.3,
          "z": 5.6
        },
        {
          "x": -245.2,
          "y": -1.1,
          "z": 12.3
        },
        {
          "x": -252.9,
          "y": -0.6,
          "z": 18.4
        },
        {
          "x": -260.5,
          "y": -0.1,
          "z": 23.5
        },
        {
          "x": -267.2,
          "y": 0.3,
          "z": 30.4
        },
        {
          "x": -273.4,
          "y": 0.6,
          "z": 36.7
        },
        {
          "x": -280.1,
          "y": 1,
          "z": 44
        },
        {
          "x": -288.4,
          "y": 1.3,
          "z": 49.7
        },
        {
          "x": -295.3,
          "y": 1.6,
          "z": 55.9
        },
        {
          "x": -302.2,
          "y": 1.6,
          "z": 63.6
        },
        {
          "x": -309.5,
          "y": 1.8,
          "z": 69.2
        },
        {
          "x": -316.9,
          "y": 2.3,
          "z": 74.7
        },
        {
          "x": -322,
          "y": 3,
          "z": 83
        },
        {
          "x": -330.6,
          "y": 4,
          "z": 88.9
        },
        {
          "x": -337.1,
          "y": 3.9,
          "z": 94.9
        }
      ]
    },
    {
      "id": "cave_8",
      "points": [
        {
          "x": 206.1,
          "y": 4.1,
          "z": -275.4
        },
        {
          "x": 210.8,
          "y": 3.6,
          "z": -265.8
        },
        {
          "x": 213.6,
          "y": 3.3,
          "z": -258
        },
        {
          "x": 217.9,
          "y": 2.9,
          "z": -250.1
        },
        {
          "x": 221.8,
          "y": 2.7,
          "z": -242.7
        },
        {
          "x": 225.4,
          "y": 3,
          "z": -232.5
        },
        {
          "x": 228.4,
          "y": 3,
          "z": -225.2
        },
        {
          "x": 233.6,
          "y": 2.5,
          "z": -216.9
        },
        {
          "x": 237.1,
          "y": 2.2,
          "z": -208.7
        },
        {
          "x": 240.9,
          "y": 1.8,
          "z": -200.2
        },
        {
          "x": 245.5,
          "y": 1.9,
          "z": -192.3
        },
        {
          "x": 248.5,
          "y": 2.7,
          "z": -182.7
        },
        {
          "x": 253.3,
          "y": 2.7,
          "z": -174.4
        },
        {
          "x": 255.6,
          "y": 2.9,
          "z": -167.6
        },
        {
          "x": 259.9,
          "y": 3,
          "z": -157.8
        },
        {
          "x": 264.3,
          "y": 2.5,
          "z": -149.8
        },
        {
          "x": 267,
          "y": 2.2,
          "z": -142.2
        },
        {
          "x": 270.8,
          "y": 2.1,
          "z": -134.8
        },
        {
          "x": 275.8,
          "y": 1.8,
          "z": -125.6
        },
        {
          "x": 280.1,
          "y": 1.4,
          "z": -117.9
        },
        {
          "x": 284,
          "y": 1.1,
          "z": -109.4
        },
        {
          "x": 287.2,
          "y": 0.6,
          "z": -101.2
        },
        {
          "x": 290.7,
          "y": 0,
          "z": -92.9
        },
        {
          "x": 294.1,
          "y": -0.5,
          "z": -84.1
        }
      ]
    },
    {
      "id": "cave_9",
      "points": [
        {
          "x": 295.2,
          "y": -0.5,
          "z": -85
        },
        {
          "x": 288.9,
          "y": 0,
          "z": -91.3
        },
        {
          "x": 281.5,
          "y": 0.2,
          "z": -98.5
        },
        {
          "x": 274.9,
          "y": 0.2,
          "z": -105.5
        },
        {
          "x": 268,
          "y": 0.4,
          "z": -111.6
        },
        {
          "x": 260.8,
          "y": 1.2,
          "z": -119.4
        },
        {
          "x": 255.2,
          "y": 2.2,
          "z": -126.8
        },
        {
          "x": 247.9,
          "y": 2.8,
          "z": -134.5
        },
        {
          "x": 240.4,
          "y": 3.4,
          "z": -140
        },
        {
          "x": 234.3,
          "y": 4.1,
          "z": -148.3
        },
        {
          "x": 227.4,
          "y": 4.7,
          "z": -154.9
        },
        {
          "x": 220.8,
          "y": 5,
          "z": -161.9
        },
        {
          "x": 213,
          "y": 5,
          "z": -168.9
        },
        {
          "x": 206.8,
          "y": 5.3,
          "z": -175.9
        },
        {
          "x": 200.2,
          "y": 5.9,
          "z": -183.2
        },
        {
          "x": 194.5,
          "y": 6.4,
          "z": -190.7
        },
        {
          "x": 187.2,
          "y": 6.6,
          "z": -198.4
        },
        {
          "x": 180.6,
          "y": 6.4,
          "z": -204.6
        },
        {
          "x": 172.5,
          "y": 5.9,
          "z": -211
        },
        {
          "x": 166.7,
          "y": 5.5,
          "z": -219.3
        },
        {
          "x": 159.6,
          "y": 5.2,
          "z": -225.3
        },
        {
          "x": 153,
          "y": 4.9,
          "z": -232.2
        },
        {
          "x": 146.5,
          "y": 4.6,
          "z": -240.9
        },
        {
          "x": 140.3,
          "y": 4.6,
          "z": -246.6
        },
        {
          "x": 131.8,
          "y": 4.8,
          "z": -253.5
        },
        {
          "x": 126.2,
          "y": 5.1,
          "z": -261.4
        },
        {
          "x": 119.1,
          "y": 5.7,
          "z": -268.2
        },
        {
          "x": 113,
          "y": 6,
          "z": -275
        },
        {
          "x": 106.3,
          "y": 6.2,
          "z": -282
        },
        {
          "x": 99.6,
          "y": 6.9,
          "z": -289.7
        }
      ]
    },
    {
      "id": "cave_10",
      "points": [
        {
          "x": -189.8,
          "y": -2,
          "z": -39.1
        },
        {
          "x": -181,
          "y": -2.7,
          "z": -40.2
        },
        {
          "x": -171.9,
          "y": -3,
          "z": -40.8
        },
        {
          "x": -161.5,
          "y": -3.2,
          "z": -42.6
        },
        {
          "x": -151.2,
          "y": -3.4,
          "z": -43.8
        },
        {
          "x": -141.9,
          "y": -3.8,
          "z": -44.9
        },
        {
          "x": -132.2,
          "y": -3.9,
          "z": -45.7
        },
        {
          "x": -123.6,
          "y": -4.2,
          "z": -46.9
        },
        {
          "x": -113,
          "y": -4.7,
          "z": -47
        },
        {
          "x": -105.1,
          "y": -4.6,
          "z": -48.3
        },
        {
          "x": -95.5,
          "y": -4.5,
          "z": -49.1
        },
        {
          "x": -85.1,
          "y": -4.2,
          "z": -50.5
        },
        {
          "x": -75,
          "y": -3.6,
          "z": -50.1
        },
        {
          "x": -67.2,
          "y": -3.1,
          "z": -50.9
        },
        {
          "x": -56.8,
          "y": -2.4,
          "z": -51.1
        },
        {
          "x": -47.5,
          "y": -1.4,
          "z": -52.7
        },
        {
          "x": -37.6,
          "y": -0.6,
          "z": -53.9
        },
        {
          "x": -29.1,
          "y": 0.4,
          "z": -55
        },
        {
          "x": -17.9,
          "y": 1,
          "z": -55.2
        },
        {
          "x": -9.3,
          "y": 1.4,
          "z": -56.7
        },
        {
          "x": 0.3,
          "y": 1.5,
          "z": -56.7
        },
        {
          "x": 9.7,
          "y": 1.3,
          "z": -58.4
        },
        {
          "x": 19.2,
          "y": 1,
          "z": -58.6
        },
        {
          "x": 29,
          "y": 1.3,
          "z": -60.7
        },
        {
          "x": 37.4,
          "y": 1.4,
          "z": -60.3
        },
        {
          "x": 47.2,
          "y": 1.9,
          "z": -62.1
        },
        {
          "x": 57.8,
          "y": 2.6,
          "z": -61.8
        },
        {
          "x": 66.1,
          "y": 3.1,
          "z": -62.8
        },
        {
          "x": 75.8,
          "y": 3.3,
          "z": -64.1
        },
        {
          "x": 84.9,
          "y": 3.2,
          "z": -65
        },
        {
          "x": 95,
          "y": 2.9,
          "z": -64.9
        },
        {
          "x": 104.3,
          "y": 2.3,
          "z": -66.5
        },
        {
          "x": 115.3,
          "y": 1.9,
          "z": -66.9
        },
        {
          "x": 123.9,
          "y": 1.6,
          "z": -69.1
        },
        {
          "x": 133,
          "y": 1.6,
          "z": -69.5
        },
        {
          "x": 143.2,
          "y": 1.4,
          "z": -70.6
        },
        {
          "x": 152.8,
          "y": 1,
          "z": -71.1
        },
        {
          "x": 162.7,
          "y": 0.8,
          "z": -72.4
        },
        {
          "x": 171.7,
          "y": 0.5,
          "z": -72.7
        },
        {
          "x": 180.2,
          "y": 0.3,
          "z": -73.7
        },
        {
          "x": 191.1,
          "y": 0.8,
          "z": -74.4
        },
        {
          "x": 199.2,
          "y": 1,
          "z": -75.8
        },
        {
          "x": 208.6,
          "y": 0.9,
          "z": -77
        },
        {
          "x": 218.1,
          "y": 0.9,
          "z": -77.7
        },
        {
          "x": 228.3,
          "y": 0.3,
          "z": -78.2
        },
        {
          "x": 237,
          "y": -0.6,
          "z": -78.2
        },
        {
          "x": 246.6,
          "y": -1.3,
          "z": -80.6
        },
        {
          "x": 257.2,
          "y": -1.5,
          "z": -80
        },
        {
          "x": 266.1,
          "y": -1.7,
          "z": -81.4
        },
        {
          "x": 275.2,
          "y": -1.3,
          "z": -81.8
        },
        {
          "x": 286,
          "y": -0.3,
          "z": -82.9
        },
        {
          "x": 295.1,
          "y": -0.5,
          "z": -83.7
        }
      ]
    },
    {
      "id": "cave_11",
      "points": [
        {
          "x": -189.8,
          "y": -2,
          "z": -39.6
        },
        {
          "x": -181.3,
          "y": -2.7,
          "z": -40.1
        },
        {
          "x": -171.9,
          "y": -3,
          "z": -39
        },
        {
          "x": -161.8,
          "y": -3.3,
          "z": -39.2
        },
        {
          "x": -151.8,
          "y": -3.5,
          "z": -39.3
        },
        {
          "x": -142.6,
          "y": -4,
          "z": -37.8
        },
        {
          "x": -132.9,
          "y": -4.2,
          "z": -38.6
        },
        {
          "x": -124.4,
          "y": -4.5,
          "z": -37.3
        },
        {
          "x": -114.1,
          "y": -5,
          "z": -36.5
        },
        {
          "x": -105.5,
          "y": -5.2,
          "z": -36
        },
        {
          "x": -94.7,
          "y": -5.2,
          "z": -36.7
        },
        {
          "x": -85.4,
          "y": -5.3,
          "z": -36
        },
        {
          "x": -77.4,
          "y": -5,
          "z": -36.4
        },
        {
          "x": -67.4,
          "y": -4.5,
          "z": -36.3
        },
        {
          "x": -57.4,
          "y": -4.2,
          "z": -35
        },
        {
          "x": -47.7,
          "y": -3.4,
          "z": -35.6
        },
        {
          "x": -39.2,
          "y": -3,
          "z": -35.5
        },
        {
          "x": -28.4,
          "y": -2.7,
          "z": -33.6
        },
        {
          "x": -19.8,
          "y": -2,
          "z": -34.8
        },
        {
          "x": -10.6,
          "y": -1.9,
          "z": -33.5
        },
        {
          "x": -1.5,
          "y": -1.7,
          "z": -33.5
        },
        {
          "x": 8.7,
          "y": -1.7,
          "z": -33.7
        },
        {
          "x": 18.7,
          "y": -2,
          "z": -32.4
        },
        {
          "x": 27.5,
          "y": -1.7,
          "z": -32.3
        },
        {
          "x": 36.6,
          "y": -1.6,
          "z": -31.5
        }
      ]
    },
    {
      "id": "cave_12",
      "points": [
        {
          "x": 37.2,
          "y": -1.5,
          "z": -32.2
        },
        {
          "x": 29.3,
          "y": -2,
          "z": -28.5
        },
        {
          "x": 18.9,
          "y": -2.6,
          "z": -26.4
        },
        {
          "x": 10.7,
          "y": -3.3,
          "z": -23.5
        },
        {
          "x": 2.3,
          "y": -3.7,
          "z": -21.2
        },
        {
          "x": -6.9,
          "y": -4.6,
          "z": -17.5
        },
        {
          "x": -15.2,
          "y": -5.5,
          "z": -15
        },
        {
          "x": -24.8,
          "y": -6.5,
          "z": -11.7
        },
        {
          "x": -33,
          "y": -6.6,
          "z": -8.6
        },
        {
          "x": -41.9,
          "y": -6.3,
          "z": -4.9
        },
        {
          "x": -50,
          "y": -6.3,
          "z": -2
        },
        {
          "x": -58,
          "y": -6.2,
          "z": 0.1
        },
        {
          "x": -68.1,
          "y": -6.1,
          "z": 4.4
        },
        {
          "x": -76.1,
          "y": -6.1,
          "z": 6.8
        },
        {
          "x": -84.5,
          "y": -5.8,
          "z": 8.9
        },
        {
          "x": -94.4,
          "y": -5.1,
          "z": 12.8
        },
        {
          "x": -101.4,
          "y": -4.5,
          "z": 15.7
        },
        {
          "x": -110.6,
          "y": -3.7,
          "z": 18.1
        },
        {
          "x": -120.5,
          "y": -3,
          "z": 21.2
        },
        {
          "x": -129,
          "y": -2.7,
          "z": 24.7
        },
        {
          "x": -136.5,
          "y": -2.7,
          "z": 26.1
        },
        {
          "x": -145.6,
          "y": -2.5,
          "z": 30.8
        },
        {
          "x": -155.2,
          "y": -2.3,
          "z": 33.2
        },
        {
          "x": -163.4,
          "y": -2.5,
          "z": 36.8
        },
        {
          "x": -171.7,
          "y": -2.8,
          "z": 39.5
        },
        {
          "x": -180.5,
          "y": -2.7,
          "z": 41.4
        },
        {
          "x": -188.4,
          "y": -3,
          "z": 44.2
        },
        {
          "x": -198.3,
          "y": -3.2,
          "z": 47.3
        },
        {
          "x": -206.6,
          "y": -2.9,
          "z": 50.7
        },
        {
          "x": -215.3,
          "y": -2.6,
          "z": 53.5
        },
        {
          "x": -223.1,
          "y": -2.2,
          "z": 56.6
        },
        {
          "x": -233.4,
          "y": -1.2,
          "z": 59.1
        },
        {
          "x": -241.7,
          "y": -0.2,
          "z": 61.6
        },
        {
          "x": -249.4,
          "y": 0.4,
          "z": 65.7
        },
        {
          "x": -259.4,
          "y": 0.8,
          "z": 67.7
        },
        {
          "x": -267.6,
          "y": 1.3,
          "z": 70.6
        },
        {
          "x": -276.4,
          "y": 1.2,
          "z": 75
        },
        {
          "x": -285,
          "y": 0.8,
          "z": 77.6
        },
        {
          "x": -294.2,
          "y": 1.1,
          "z": 79.9
        },
        {
          "x": -302.4,
          "y": 1.4,
          "z": 82.6
        },
        {
          "x": -311.3,
          "y": 1.5,
          "z": 86.8
        },
        {
          "x": -319.3,
          "y": 2.4,
          "z": 89.8
        },
        {
          "x": -327.5,
          "y": 3.6,
          "z": 92.5
        },
        {
          "x": -336.7,
          "y": 3.9,
          "z": 95.4
        }
      ]
    },
    {
      "id": "village_cave_13",
      "points": [
        {
          "x": 0.3,
          "y": -7.1,
          "z": -0.8
        },
        {
          "x": 6.9,
          "y": -6.2,
          "z": -5.9
        },
        {
          "x": 11.8,
          "y": -4.8,
          "z": -11.7
        },
        {
          "x": 18.2,
          "y": -3.6,
          "z": -16.5
        },
        {
          "x": 24.4,
          "y": -2.8,
          "z": -20.6
        },
        {
          "x": 30,
          "y": -2.2,
          "z": -25.7
        },
        {
          "x": 36.6,
          "y": -1.5,
          "z": -32.9
        }
      ]
    },
    {
      "id": "village_cave_14",
      "points": [
        {
          "x": 0.3,
          "y": -7.1,
          "z": 0.7
        },
        {
          "x": -2.2,
          "y": -7.5,
          "z": 9
        },
        {
          "x": -5.7,
          "y": -8.2,
          "z": 17.7
        },
        {
          "x": -8.4,
          "y": -8.5,
          "z": 25.4
        },
        {
          "x": -11.3,
          "y": -8.6,
          "z": 35
        },
        {
          "x": -12.7,
          "y": -8.7,
          "z": 43.5
        },
        {
          "x": -16.8,
          "y": -8.8,
          "z": 53
        }
      ]
    }
  ],
  "safeZones": [
    {
      "type": "circle",
      "x": 0,
      "z": 0,
      "radius": 55
    }
  ],
  "interactive": [
    {
      "type": "chapter_quest",
      "chapterQuestId": "chapter_2_forest_of_doubt",
      "position": {
        "x": 50,
        "z": 0
      }
    }
  ]
}